{
    "status": 1,
    "message": "",
    "chart_data": {
        "data": [
            [
                [
                    "07-06",
                    2311
                ],
                [
                    "07-07",
                    3533
                ],
                [
                    "07-08",
                    1457
                ],
                [
                    "07-09",
                    1362
                ],
                [
                    "07-10",
                    4807
                ],
                [
                    "07-11",
                    4170
                ],
                [
                    "07-12",
                    3862
                ],
                [
                    "07-13",
                    3336
                ],
                [
                    "07-14",
                    4056
                ],
                [
                    "07-15",
                    3211
                ],
                [
                    "07-16",
                    2273
                ],
                [
                    "07-17",
                    2607
                ],
                [
                    "07-18",
                    2707
                ],
                [
                    "07-19",
                    3206
                ],
                [
                    "07-20",
                    3017
                ],
                [
                    "07-21",
                    2662
                ],
                [
                    "07-24",
                    2932
                ],
                [
                    "07-25",
                    1941
                ],
                [
                    "07-26",
                    2335
                ],
                [
                    "07-27",
                    2449
                ],
                [
                    "07-28",
                    2292
                ],
                [
                    "07-29",
                    625
                ],
                [
                    "07-30",
                    1300
                ],
                [
                    "07-31",
                    3557
                ]
            ],
            [
                [
                    "07-06",
                    160
                ],
                [
                    "07-07",
                    270
                ],
                [
                    "07-08",
                    189
                ],
                [
                    "07-09",
                    164
                ],
                [
                    "07-10",
                    312
                ],
                [
                    "07-11",
                    263
                ],
                [
                    "07-12",
                    248
                ],
                [
                    "07-13",
                    302
                ],
                [
                    "07-14",
                    347
                ],
                [
                    "07-15",
                    381
                ],
                [
                    "07-16",
                    250
                ],
                [
                    "07-17",
                    303
                ],
                [
                    "07-18",
                    234
                ],
                [
                    "07-19",
                    180
                ],
                [
                    "07-20",
                    190
                ],
                [
                    "07-21",
                    240
                ],
                [
                    "07-24",
                    235
                ],
                [
                    "07-25",
                    279
                ],
                [
                    "07-26",
                    293
                ],
                [
                    "07-27",
                    286
                ],
                [
                    "07-28",
                    266
                ],
                [
                    "07-29",
                    126
                ],
                [
                    "07-30",
                    169
                ],
                [
                    "07-31",
                    295
                ]
            ]
        ],
        "x_categories": [
            "07-01",
            "07-02",
            "07-03",
            "07-04",
            "07-05",
            "07-06",
            "07-07",
            "07-08",
            "07-09",
            "07-10",
            "07-11",
            "07-12",
            "07-13",
            "07-14",
            "07-15",
            "07-16",
            "07-17",
            "07-18",
            "07-19",
            "07-20",
            "07-21",
            "07-22",
            "07-23",
            "07-24",
            "07-25",
            "07-26",
            "07-27",
            "07-28",
            "07-29",
            "07-30",
            "07-31"
        ]
    },
    "table_data": [
        [
            "07-06",
            2311,
            160,
            null
        ],
        [
            "07-07",
            3533,
            270,
            null
        ],
        [
            "07-08",
            1457,
            189,
            null
        ],
        [
            "07-09",
            1362,
            164,
            null
        ],
        [
            "07-10",
            4807,
            312,
            null
        ],
        [
            "07-11",
            4170,
            263,
            null
        ],
        [
            "07-12",
            3862,
            248,
            null
        ],
        [
            "07-13",
            3336,
            302,
            null
        ],
        [
            "07-14",
            4056,
            347,
            null
        ],
        [
            "07-15",
            3211,
            381,
            null
        ],
        [
            "07-16",
            2273,
            250,
            null
        ],
        [
            "07-17",
            2607,
            303,
            null
        ],
        [
            "07-18",
            2707,
            234,
            null
        ],
        [
            "07-19",
            3206,
            180,
            null
        ],
        [
            "07-20",
            3017,
            190,
            null
        ],
        [
            "07-21",
            2662,
            240,
            null
        ],
        [
            "07-24",
            2932,
            235,
            null
        ],
        [
            "07-25",
            1941,
            279,
            null
        ],
        [
            "07-26",
            2335,
            293,
            null
        ],
        [
            "07-27",
            2449,
            286,
            null
        ],
        [
            "07-28",
            2292,
            266,
            null
        ],
        [
            "07-29",
            625,
            126,
            null
        ],
        [
            "07-30",
            1300,
            169,
            null
        ],
        [
            "07-31",
            3557,
            295,
            null
        ],
        [
            "汇总",
            66008,
            5982,
            null
        ]
    ]
}